synthesia/__init__.py
synthesia/datasets/__init__.py
synthesia/datasets/facebook-ads.v1/accounts.csv
synthesia/datasets/facebook-ads.v1/ad_creatives.csv
synthesia/datasets/facebook-ads.v1/ad_insights.csv
synthesia/datasets/facebook-ads.v1/ad_insights_action_type.csv
synthesia/datasets/facebook-ads.v1/ad_label_assignments.csv
synthesia/datasets/facebook-ads.v1/ad_labels.csv
synthesia/datasets/facebook-ads.v1/ads.csv
synthesia/datasets/facebook-ads.v1/adsets.csv
synthesia/datasets/facebook-ads.v1/audiences.csv
synthesia/datasets/facebook-ads.v1/campaigns.csv
synthesia/datasets/google-ads.v1/account_labels.csv
synthesia/datasets/google-ads.v1/ad_creatives.csv
synthesia/datasets/google-ads.v1/ad_group_labels.csv
synthesia/datasets/google-ads.v1/ad_group_performance_report.csv
synthesia/datasets/google-ads.v1/ad_groups.csv
synthesia/datasets/google-ads.v1/ad_labels.csv
synthesia/datasets/google-ads.v1/ad_performance_report.csv
synthesia/datasets/google-ads.v1/ads.csv
synthesia/datasets/google-ads.v1/attribution_report.csv
synthesia/datasets/google-ads.v1/audiences.csv
synthesia/datasets/google-ads.v1/bidding_strategies.csv
synthesia/datasets/google-ads.v1/campaign_labels.csv
synthesia/datasets/google-ads.v1/campaign_performance_report.csv
synthesia/datasets/google-ads.v1/campaigns.csv
synthesia/datasets/google-ads.v1/conversion_actions.csv
synthesia/datasets/google-ads.v1/conversion_report.csv
synthesia/datasets/google-ads.v1/customers.csv
synthesia/datasets/google-ads.v1/daily_spend_report.csv
synthesia/datasets/google-ads.v1/devices.csv
synthesia/datasets/google-ads.v1/geo_targets.csv
synthesia/datasets/google-ads.v1/keyword_performance_report.csv
synthesia/datasets/google-ads.v1/keywords.csv
synthesia/datasets/google-ads.v1/placement_performance_report.csv
synthesia/datasets/google-ads.v1/search_query_performance_report.csv
synthesia/datasets/google-ads.v1/shared_budget.csv
synthesia/datasets/google-analytics-4.v1/device.csv
synthesia-0.2.1.dist-info/WHEEL
synthesia-0.2.1.dist-info/entry_points.txt
synthesia-0.2.1.dist-info/METADATA
synthesia-0.2.1.dist-info/RECORD
