Metadata-Version: 2.3
Name: synthesia
Version: 0.2.1
Summary: Add your description here
Requires-Dist: dlt[bigquery]>=1.15.0
Requires-Dist: google-cloud-bigquery-storage>=2.32.0
Requires-Dist: grpcio==1.73.1
Requires-Dist: pandas>=2.3.1
Requires-Dist: pyarrow>=21.0.0
Requires-Dist: typer>=0.16.0
Requires-Python: >=3.12
